{
"type": "FeatureCollection",
"crs": { "type": "name", "properties": { "name": "urn:ogc:def:crs:OGC:1.3:CRS84" } },
"features": [
{ "type": "Feature", "properties": { "id": 0 }, "geometry": { "type": "Point", "coordinates": [ -65.925753, 4.562538 ] } },
{ "type": "Feature", "properties": { "id": 3 }, "geometry": { "type": "Point", "coordinates": [ -65.918159, 4.562538 ] } },
{ "type": "Feature", "properties": { "id": 6 }, "geometry": { "type": "Point", "coordinates": [ -66.918448, 3.892325 ] } },
{ "type": "Feature", "properties": { "id": 9 }, "geometry": { "type": "Point", "coordinates": [ -66.8107255, 3.7048145 ] } },
{ "type": "Feature", "properties": { "id": 12 }, "geometry": { "type": "Point", "coordinates": [ -66.808212, 3.71494 ] } },
{ "type": "Feature", "properties": { "id": 15 }, "geometry": { "type": "Point", "coordinates": [ -66.8107255, 3.71494 ] } },
{ "type": "Feature", "properties": { "id": 18 }, "geometry": { "type": "Point", "coordinates": [ -66.813239, 3.71494 ] } },
{ "type": "Feature", "properties": { "id": 21 }, "geometry": { "type": "Point", "coordinates": [ -66.7726495, 3.7223485 ] } },
{ "type": "Feature", "properties": { "id": 24 }, "geometry": { "type": "Point", "coordinates": [ -66.745195, 3.70463 ] } },
{ "type": "Feature", "properties": { "id": 27 }, "geometry": { "type": "Point", "coordinates": [ -66.91342, 3.887262 ] } },
{ "type": "Feature", "properties": { "id": 30 }, "geometry": { "type": "Point", "coordinates": [ -66.559067, 3.5369995 ] } },
{ "type": "Feature", "properties": { "id": 33 }, "geometry": { "type": "Point", "coordinates": [ -66.8004865, 3.7122235 ] } },
{ "type": "Feature", "properties": { "id": 36 }, "geometry": { "type": "Point", "coordinates": [ -66.8055125, 3.714755 ] } },
{ "type": "Feature", "properties": { "id": 39 }, "geometry": { "type": "Point", "coordinates": [ -66.767814, 3.7198175 ] } },
{ "type": "Feature", "properties": { "id": 42 }, "geometry": { "type": "Point", "coordinates": [ -66.915934, 3.892325 ] } },
{ "type": "Feature", "properties": { "id": 45 }, "geometry": { "type": "Point", "coordinates": [ -66.925991, 3.8999195 ] } },
{ "type": "Feature", "properties": { "id": 48 }, "geometry": { "type": "Point", "coordinates": [ -66.812864, 3.8187275 ] } },
{ "type": "Feature", "properties": { "id": 51 }, "geometry": { "type": "Point", "coordinates": [ -66.8029995, 3.7096925 ] } },
{ "type": "Feature", "properties": { "id": 54 }, "geometry": { "type": "Point", "coordinates": [ -66.808212, 3.707346 ] } },
{ "type": "Feature", "properties": { "id": 57 }, "geometry": { "type": "Point", "coordinates": [ -66.918448, 3.902451 ] } },
{ "type": "Feature", "properties": { "id": 60 }, "geometry": { "type": "Point", "coordinates": [ -66.564091, 3.5369995 ] } },
{ "type": "Feature", "properties": { "id": 63 }, "geometry": { "type": "Point", "coordinates": [ -66.908391, 3.882199 ] } },
{ "type": "Feature", "properties": { "id": 66 }, "geometry": { "type": "Point", "coordinates": [ -66.797973, 3.714755 ] } },
{ "type": "Feature", "properties": { "id": 69 }, "geometry": { "type": "Point", "coordinates": [ -66.7803805, 3.7198175 ] } },
{ "type": "Feature", "properties": { "id": 72 }, "geometry": { "type": "Point", "coordinates": [ -66.920962, 3.8948565 ] } },
{ "type": "Feature", "properties": { "id": 75 }, "geometry": { "type": "Point", "coordinates": [ -66.8157525, 3.6997515 ] } },
{ "type": "Feature", "properties": { "id": 78 }, "geometry": { "type": "Point", "coordinates": [ -66.564091, 3.5344685 ] } },
{ "type": "Feature", "properties": { "id": 81 }, "geometry": { "type": "Point", "coordinates": [ -66.915934, 3.8847305 ] } },
{ "type": "Feature", "properties": { "id": 84 }, "geometry": { "type": "Point", "coordinates": [ -66.7753535, 3.7198175 ] } },
{ "type": "Feature", "properties": { "id": 87 }, "geometry": { "type": "Point", "coordinates": [ -66.556555, 3.5597775 ] } },
{ "type": "Feature", "properties": { "id": 90 }, "geometry": { "type": "Point", "coordinates": [ -66.813239, 3.7124085 ] } },
{ "type": "Feature", "properties": { "id": 93 }, "geometry": { "type": "Point", "coordinates": [ -66.7701365, 3.7274115 ] } },
{ "type": "Feature", "properties": { "id": 96 }, "geometry": { "type": "Point", "coordinates": [ -66.8029995, 3.7071615 ] } },
{ "type": "Feature", "properties": { "id": 99 }, "geometry": { "type": "Point", "coordinates": [ -66.8107255, 3.7124085 ] } },
{ "type": "Feature", "properties": { "id": 102 }, "geometry": { "type": "Point", "coordinates": [ -66.920962, 3.897388 ] } },
{ "type": "Feature", "properties": { "id": 105 }, "geometry": { "type": "Point", "coordinates": [ -66.813239, 3.7048145 ] } }
]
}
